tif_stats.py
tif_stats-0.12.dist-info/DESCRIPTION.rst
tif_stats-0.12.dist-info/METADATA
tif_stats-0.12.dist-info/RECORD
tif_stats-0.12.dist-info/WHEEL
tif_stats-0.12.dist-info/metadata.json
tif_stats-0.12.dist-info/top_level.txt
