Metadata-Version: 2.0
Name: tif-stats
Version: 0.12
Summary: Generates basic statistics on a geojson clipped tif image
Home-page: UNKNOWN
Author: Development Seed
Author-email: aimee@developmentseed.org,nana@developmentseed.org
License: MIT
Platform: UNKNOWN
